odoo8_addon_sale_stock_commission-8.0.1.0.0.99.dev13-py2.7-nspkg.pth
odoo8_addon_sale_stock_commission-8.0.1.0.0.99.dev13.dist-info/DESCRIPTION.rst
odoo8_addon_sale_stock_commission-8.0.1.0.0.99.dev13.dist-info/METADATA
odoo8_addon_sale_stock_commission-8.0.1.0.0.99.dev13.dist-info/RECORD
odoo8_addon_sale_stock_commission-8.0.1.0.0.99.dev13.dist-info/WHEEL
odoo8_addon_sale_stock_commission-8.0.1.0.0.99.dev13.dist-info/metadata.json
odoo8_addon_sale_stock_commission-8.0.1.0.0.99.dev13.dist-info/namespace_packages.txt
odoo8_addon_sale_stock_commission-8.0.1.0.0.99.dev13.dist-info/top_level.txt
odoo_addons/sale_stock_commission/README.rst
odoo_addons/sale_stock_commission/__init__.py
odoo_addons/sale_stock_commission/__openerp__.py
odoo_addons/sale_stock_commission/i18n/ca.po
odoo_addons/sale_stock_commission/i18n/de.po
odoo_addons/sale_stock_commission/i18n/es.po
odoo_addons/sale_stock_commission/i18n/es_AR.po
odoo_addons/sale_stock_commission/i18n/es_MX.po
odoo_addons/sale_stock_commission/i18n/fi.po
odoo_addons/sale_stock_commission/i18n/fr.po
odoo_addons/sale_stock_commission/i18n/hr.po
odoo_addons/sale_stock_commission/i18n/it.po
odoo_addons/sale_stock_commission/i18n/pt.po
odoo_addons/sale_stock_commission/i18n/pt_BR.po
odoo_addons/sale_stock_commission/i18n/sale_stock_commission.pot
odoo_addons/sale_stock_commission/i18n/sl.po
odoo_addons/sale_stock_commission/i18n/tr.po
odoo_addons/sale_stock_commission/i18n/tr_TR.po
odoo_addons/sale_stock_commission/models/__init__.py
odoo_addons/sale_stock_commission/models/stock_move.py
odoo_addons/sale_stock_commission/static/description/icon.png
odoo_addons/sale_stock_commission/static/description/icon.svg
