Metadata-Version: 2.0
Name: odoo8-addon-sale-stock-commission
Version: 8.0.1.0.0.99.dev13
Summary: Sale stock commissions
Home-page: UNKNOWN
Author: Serv. Tecnol. Avanzados - Pedro M. Baeza
Author-email: UNKNOWN
License: AGPL-3
Platform: UNKNOWN
Classifier: Programming Language :: Python
Classifier: Framework :: Odoo
Classifier: License :: OSI Approved :: GNU Affero General Public License v3
Requires-Python: ~=2.7
Requires-Dist: odoo (<9.0a,>=8.0a)
Requires-Dist: odoo8-addon-sale-commission
